common/__init__.py
common/apihelper/__init__.py
common/apihelper/localpushhelper.py
common/apihelper/sharefactoryhelper.py
common/business/__init__.py
common/business/devicebusiness.py
common/business/farmbusiness.py
common/business/imagebusiness.py
common/business/weightbusiness.py
common/data/__init__.py
common/data/basemodel.py
common/data/customermodel.py
common/data/factorymodel.py
common/data/farmmodel.py
common/data/qrcodemodel.py
common/data/shipmentlistmodel.py
common/data/shipmentmodel.py
common/data/specificationmodel.py
common/data/weightmodel.py
common/fhx711/__init__.py
common/fhx711/calibration.py
common/fhx711/hx711.py
common/fhx711/qrcodescanner.py
common/fhx711/scannerimage.py
common/fhx711/voice.py
common/mqtt/__init__.py
common/mqtt/action_enum.py
common/mqtt/action_service.py
common/mqtt/mqtt_onenet.py
common/repositories/__init__.py
common/repositories/create.py
common/repositories/customerrepository.py
common/repositories/factoryrepository.py
common/repositories/farmrepository.py
common/repositories/mysqldb.py
common/repositories/qrcoderepository.py
common/repositories/shipmentlistrepository.py
common/repositories/shipmentrepository.py
common/repositories/specificationrepository.py
common/repositories/sqlitedb.py
common/repositories/weightrepository.py
common/view/__init__.py
common/view/customerview.py
common/view/factoryview.py
common/view/farmview.py
common/view/qrcodeview.py
common/view/shipmentlistparameter.py
common/view/syncweightview.py
common/view/weightparameter.py
common/view/weightview.py
common/viewdata/__init__.py
common/viewdata/customerviewdata.py
common/viewdata/factoryviewdata.py
common/viewdata/farmviewdata.py
common/viewdata/qrcodeviewdata.py
common/viewdata/weightviewdata.py
bndrpi-0.0.3.dist-info/METADATA
bndrpi-0.0.3.dist-info/WHEEL
bndrpi-0.0.3.dist-info/top_level.txt
bndrpi-0.0.3.dist-info/RECORD
