Metadata-Version: 2.1
Name: bndrpi
Version: 0.0.3
Summary: 共享仓电子秤称公共组件
Home-page: UNKNOWN
Author: ZQK
Author-email: UNKNOWN
License: UNKNOWN
Platform: UNKNOWN
